gsmtasks/__init__.py
gsmtasks/client.py
gsmtasks/components/__init__.py
gsmtasks/components/schemas/Account/__init__.py
gsmtasks/components/schemas/Account/properties/__init__.py
gsmtasks/components/schemas/Account/properties/auto_assign_rotate/__init__.py
gsmtasks/components/schemas/Account/properties/auto_assign_rotate/schema.py
gsmtasks/components/schemas/Account/properties/task_expiry_duration_from_complete_after/__init__.py
gsmtasks/components/schemas/Account/properties/task_expiry_duration_from_complete_after/schema.py
gsmtasks/components/schemas/Account/properties/task_expiry_duration_from_complete_before/__init__.py
gsmtasks/components/schemas/Account/properties/task_expiry_duration_from_complete_before/schema.py
gsmtasks/components/schemas/Account/schema.py
gsmtasks/components/schemas/AccountOwnerChange/__init__.py
gsmtasks/components/schemas/AccountOwnerChange/schema.py
gsmtasks/components/schemas/AccountRole/__init__.py
gsmtasks/components/schemas/AccountRole/schema.py
gsmtasks/components/schemas/AccountRoleActivation/__init__.py
gsmtasks/components/schemas/AccountRoleActivation/schema.py
gsmtasks/components/schemas/AccountRoleToken/__init__.py
gsmtasks/components/schemas/AccountRoleToken/schema.py
gsmtasks/components/schemas/AccountStripePaymentMethodAttach/__init__.py
gsmtasks/components/schemas/AccountStripePaymentMethodAttach/schema.py
gsmtasks/components/schemas/AccountStripePaymentMethodDetach/__init__.py
gsmtasks/components/schemas/AccountStripePaymentMethodDetach/schema.py
gsmtasks/components/schemas/AccountStripePaymentMethodSetDefault/__init__.py
gsmtasks/components/schemas/AccountStripePaymentMethodSetDefault/schema.py
gsmtasks/components/schemas/AccountStripeSetupAttemptGet/__init__.py
gsmtasks/components/schemas/AccountStripeSetupAttemptGet/schema.py
gsmtasks/components/schemas/AccountStripeSetupIntentCreate/__init__.py
gsmtasks/components/schemas/AccountStripeSetupIntentCreate/schema.py
gsmtasks_client-0.5.0.dist-info/METADATA
gsmtasks_client-0.5.0.dist-info/WHEEL
gsmtasks_client-0.5.0.dist-info/RECORD
