Metadata-Version: 2.1
Name: gsmtasks-client
Version: 0.5.0
Summary: Client library for https://api.gsmtasks.com/ .
Home-page: https://github.com/lapidary-library/gsmtasks
License: 0BSD
Requires-Python: >=3.9,<4.0
Classifier: License :: OSI Approved
Classifier: Programming Language :: Python :: 3
Classifier: Programming Language :: Python :: 3.9
Classifier: Programming Language :: Python :: 3.10
Classifier: Programming Language :: Python :: 3.11
Classifier: Programming Language :: Python :: 3.12
Requires-Dist: lapidary (>=0.12.0,<0.13.0)
Project-URL: Repository, https://github.com/lapidary-library/gsmtasks
